src/mcp_server_aws_resources/__init__.py
src/mcp_server_aws_resources/server.py
orange_mcp_server_aws_resources-0.1.0.dist-info/METADATA
orange_mcp_server_aws_resources-0.1.0.dist-info/WHEEL
orange_mcp_server_aws_resources-0.1.0.dist-info/licenses/LICENSE
orange_mcp_server_aws_resources-0.1.0.dist-info/RECORD
